testranunculus/__init__.py
testranunculus/__main__.py
testranunculus/app.py
testranunculus/available_functions.py
testranunculus/blueprint_code.py
testranunculus/blueprint_text.py
testranunculus/documents_management.py
testranunculus/file_management.py
testranunculus/function_calling_spec_maker.py
testranunculus/function_management.py
testranunculus/helpers.py
testranunculus/llm_functions.py
testranunculus/main.py
testranunculus/menu.py
testranunculus/project_management.py
testranunculus/project_management_data.py
testranunculus/prompts.py
testranunculus/requirements_with_chat.py
testranunculus/scrap.py
testranunculus/session_state_management.py
testranunculus/simple_auth.py
testranunculus/plugins/__init__.py
testranunculus/plugins/create_content_with_llms.py
testranunculus/plugins/custom_llm.py
testranunculus/plugins/data_widgets.py
testranunculus/plugins/llm_functions.py
testranunculus/plugins/llms.py
testranunculus/tools/__init__.py
testranunculus/tools/google_search.py
testranunculus/tools/location_api.py
testranunculus/tools/yt_search.py
testranunculus-1.2.2.dist-info/LICENSE
testranunculus-1.2.2.dist-info/METADATA
testranunculus-1.2.2.dist-info/WHEEL
testranunculus-1.2.2.dist-info/entry_points.txt
testranunculus-1.2.2.dist-info/top_level.txt
testranunculus-1.2.2.dist-info/RECORD
