Metadata-Version: 2.1
Name: testranunculus
Version: 1.2.2
Summary: A brief description of your package
Home-page: https://github.com/project-typebuild/typebuild
Author: iRanadheer
Author-email: neneranadheer@gmail.com
Classifier: Development Status :: 3 - Alpha
Classifier: Intended Audience :: Developers
Classifier: License :: Other/Proprietary License
Classifier: Programming Language :: Python :: 3
Classifier: Programming Language :: Python :: 3.6
Classifier: Programming Language :: Python :: 3.7
Classifier: Programming Language :: Python :: 3.8
License-File: LICENSE
Requires-Dist: aiohttp (==3.8.5)
Requires-Dist: aiosignal (==1.3.1)
Requires-Dist: altair (==5.0.1)
Requires-Dist: anthropic (==0.3.8)
Requires-Dist: anyio (==3.7.1)
Requires-Dist: async-timeout (==4.0.2)
Requires-Dist: attrs (==23.1.0)
Requires-Dist: beautifulsoup4 (==4.12.2)
Requires-Dist: blinker (==1.6.2)
Requires-Dist: cachetools (==5.3.1)
Requires-Dist: certifi (==2023.7.22)
Requires-Dist: charset-normalizer (==3.2.0)
Requires-Dist: click (==8.1.6)
Requires-Dist: contourpy (==1.1.0)
Requires-Dist: cycler (==0.11.0)
Requires-Dist: dataclasses-json (==0.5.14)
Requires-Dist: decorator (==5.1.1)
Requires-Dist: distro (==1.8.0)
Requires-Dist: exceptiongroup (==1.1.2)
Requires-Dist: extra-streamlit-components (==0.1.56)
Requires-Dist: Faker (==19.3.1)
Requires-Dist: favicon (==0.7.0)
Requires-Dist: fonttools (==4.42.0)
Requires-Dist: frozenlist (==1.4.0)
Requires-Dist: fsspec (==2023.6.0)
Requires-Dist: gitdb (==4.0.10)
Requires-Dist: GitPython (==3.1.32)
Requires-Dist: greenlet (==2.0.2)
Requires-Dist: h11 (==0.14.0)
Requires-Dist: htbuilder (==0.6.1)
Requires-Dist: httpcore (==0.17.3)
Requires-Dist: httpx (==0.24.1)
Requires-Dist: idna (==3.4)
Requires-Dist: importlib-metadata (==6.8.0)
Requires-Dist: Jinja2 (==3.1.2)
Requires-Dist: joblib (==1.3.1)
Requires-Dist: jsonschema (==4.18.6)
Requires-Dist: jsonschema-specifications (==2023.7.1)
Requires-Dist: kiwisolver (==1.4.4)
Requires-Dist: langchain (==0.0.275)
Requires-Dist: langsmith (==0.0.27)
Requires-Dist: llama-index (==0.8.11.post3)
Requires-Dist: lxml (==4.9.3)
Requires-Dist: Markdown (==3.4.4)
Requires-Dist: markdown-it-py (==3.0.0)
Requires-Dist: markdownlit (==0.0.7)
Requires-Dist: MarkupSafe (==2.1.3)
Requires-Dist: marshmallow (==3.20.1)
Requires-Dist: matplotlib (==3.7.2)
Requires-Dist: mdurl (==0.1.2)
Requires-Dist: more-itertools (==10.1.0)
Requires-Dist: multidict (==6.0.4)
Requires-Dist: mypy-extensions (==1.0.0)
Requires-Dist: nest-asyncio (==1.5.7)
Requires-Dist: numexpr (==2.8.5)
Requires-Dist: numpy
Requires-Dist: openai (==0.27.8)
Requires-Dist: packaging (==23.1)
Requires-Dist: pandas (==2.0.3)
Requires-Dist: Pillow (==9.5.0)
Requires-Dist: protobuf (==4.23.4)
Requires-Dist: pyarrow (==12.0.1)
Requires-Dist: pydantic (==1.10.12)
Requires-Dist: pydeck (==0.8.0)
Requires-Dist: Pygments (==2.15.1)
Requires-Dist: pymdown-extensions (==10.3)
Requires-Dist: Pympler (==1.0.1)
Requires-Dist: pyparsing (==3.0.9)
Requires-Dist: python-dateutil (==2.8.2)
Requires-Dist: pytz (==2023.3)
Requires-Dist: pytz-deprecation-shim (==0.1.0.post0)
Requires-Dist: PyYAML (==6.0.1)
Requires-Dist: referencing (==0.30.1)
Requires-Dist: regex (==2023.8.8)
Requires-Dist: requests (==2.31.0)
Requires-Dist: rich (==13.5.2)
Requires-Dist: rpds-py (==0.9.2)
Requires-Dist: scikit-learn (==1.3.0)
Requires-Dist: scipy
Requires-Dist: seaborn (==0.12.2)
Requires-Dist: six (==1.16.0)
Requires-Dist: smmap (==5.0.0)
Requires-Dist: sniffio (==1.3.0)
Requires-Dist: soupsieve (==2.4.1)
Requires-Dist: SQLAlchemy (==2.0.20)
Requires-Dist: st-annotated-text (==4.0.0)
Requires-Dist: streamlit (==1.26.0)
Requires-Dist: streamlit-ace (==0.1.1)
Requires-Dist: streamlit-camera-input-live (==0.2.0)
Requires-Dist: streamlit-card (==0.0.61)
Requires-Dist: streamlit-datalist (==0.0.5)
Requires-Dist: streamlit-embedcode (==0.1.2)
Requires-Dist: streamlit-extras (==0.3.0)
Requires-Dist: streamlit-faker (==0.0.2)
Requires-Dist: streamlit-image-coordinates (==0.1.6)
Requires-Dist: streamlit-keyup (==0.2.0)
Requires-Dist: streamlit-option-menu (==0.3.6)
Requires-Dist: streamlit-toggle-switch (==1.0.2)
Requires-Dist: streamlit-vertical-slider (==1.0.2)
Requires-Dist: tabulate (==0.9.0)
Requires-Dist: tenacity (==8.2.2)
Requires-Dist: threadpoolctl (==3.2.0)
Requires-Dist: tiktoken (==0.4.0)
Requires-Dist: tokenizers (==0.13.3)
Requires-Dist: toml (==0.10.2)
Requires-Dist: toolz (==0.12.0)
Requires-Dist: tornado (==6.3.2)
Requires-Dist: tqdm (==4.65.0)
Requires-Dist: typing-inspect (==0.9.0)
Requires-Dist: typing-extensions (==4.7.1)
Requires-Dist: tzdata (==2023.3)
Requires-Dist: tzlocal (==4.3.1)
Requires-Dist: urllib3 (==1.26.16)
Requires-Dist: validators (==0.20.0)
Requires-Dist: watchdog (==3.0.0)
Requires-Dist: yarl (==1.9.2)
Requires-Dist: zipp (==3.16.2)
Requires-Dist: chardet
